piccolo_theme/__init__.py
piccolo_theme/globaltoc.html
piccolo_theme/layout.html
piccolo_theme/snippets.py
piccolo_theme/theme.conf
piccolo_theme/components/dark_mode_toggle.html
piccolo_theme/components/notification_banner.html
piccolo_theme/components/source_link.html
piccolo_theme/static/basic_mod.css
piccolo_theme/static/basic_mod.css.map
piccolo_theme/static/fonts/roboto/LICENSE.txt
piccolo_theme/static/fonts/roboto/roboto-bold.woff2
piccolo_theme/static/fonts/roboto/roboto-italic.woff2
piccolo_theme/static/fonts/roboto/roboto.woff2
piccolo_theme/static/fonts/roboto-mono/LICENSE.txt
piccolo_theme/static/fonts/roboto-mono/roboto-mono-bold-italic.woff2
piccolo_theme/static/fonts/roboto-mono/roboto-mono-bold.woff2
piccolo_theme/static/fonts/roboto-mono/roboto-mono-italic.woff2
piccolo_theme/static/fonts/roboto-mono/roboto-mono.woff2
piccolo_theme/static/js/petite-vue.js
piccolo_theme/static/js/theme.js
piccolo_theme-0.23.0.dist-info/LICENSE
piccolo_theme-0.23.0.dist-info/METADATA
piccolo_theme-0.23.0.dist-info/WHEEL
piccolo_theme-0.23.0.dist-info/entry_points.txt
piccolo_theme-0.23.0.dist-info/top_level.txt
piccolo_theme-0.23.0.dist-info/RECORD
